README.md
setup.py
pyhtmlchart/__init__.py
pyhtmlchart.egg-info/PKG-INFO
pyhtmlchart.egg-info/SOURCES.txt
pyhtmlchart.egg-info/dependency_links.txt
pyhtmlchart.egg-info/top_level.txt
pyhtmlchart/area_chart/__init__.py
pyhtmlchart/bar_chart/__init__.py
pyhtmlchart/column_chart/__init__.py
pyhtmlchart/line_chart/__init__.py
pyhtmlchart/multiple_charts/__init__.py
pyhtmlchart/pie_chart/__init__.py
pyhtmlchart/table/__init__.py