Metadata-Version: 2.1
Name: pyhtmlchart
Version: 1.0
Summary: Python library to make Google Charts.
Home-page: https://github.com/Sid72020123/pyhtmlchart
Author: Siddhesh Chavan
Author-email: siddheshchavan2020@gmail.com
License: MIT
Keywords: make-google-chart
Platform: UNKNOWN
Classifier: Development Status :: 5 - Production/Stable
Classifier: Intended Audience :: Education
Classifier: Operating System :: Microsoft :: Windows :: Windows 10
Classifier: License :: OSI Approved :: MIT License
Classifier: Programming Language :: Python :: 3
